{"tileGeometry":{"type":"BufferGeometry","uuid":"3222AA7C-2CD6-4091-9E97-E9938871B38B","data":{"attributes":{"position":{"type":"Float32Array","itemSize":3,"normalized":false,"array":[]},"normal":{"type":"Float32Array","itemSize":3,"normalized":false,"array":[]},"color":{"type":"Float32Array","itemSize":3,"normalized":false,"array":[]},"uv":{"type":"Float32Array","itemSize":2,"normalized":false,"array":[]},"ao":{"type":"Float32Array","itemSize":1,"normalized":false,"array":[]},"blocklight":{"type":"Float32Array","itemSize":1,"normalized":false,"array":[]},"sunlight":{"type":"Float32Array","itemSize":1,"normalized":false,"array":[]}},"groups":[]}}}